misaki/__init__.py
misaki/cutlet.py
misaki/en.py
misaki/espeak.py
misaki/ja.py
misaki/ko.py
misaki/num2kana.py
misaki/num2vi.py
misaki/token.py
misaki/tone_sandhi.py
misaki/transcription.py
misaki/vi.py
misaki/zh.py
misaki/zh_frontend.py
misaki/data/__init__.py
misaki/data/gb_gold.json
misaki/data/gb_silver.json
misaki/data/ja_words.txt
misaki/data/us_gold.json
misaki/data/us_silver.json
misaki/data/vi_symbols.json
misaki/data/vi_teencode.json
misaki/g2pkc/README.md
misaki/g2pkc/__init__.py
misaki/g2pkc/english.py
misaki/g2pkc/g2pk.py
misaki/g2pkc/idioms.txt
misaki/g2pkc/numerals.py
misaki/g2pkc/regular.py
misaki/g2pkc/rules.txt
misaki/g2pkc/special.py
misaki/g2pkc/table.csv
misaki/g2pkc/utils.py
misaki/zh_normalization/README.md
misaki/zh_normalization/__init__.py
misaki/zh_normalization/char_convert.py
misaki/zh_normalization/chronology.py
misaki/zh_normalization/constants.py
misaki/zh_normalization/num.py
misaki/zh_normalization/phonecode.py
misaki/zh_normalization/quantifier.py
misaki/zh_normalization/text_normalization.py
misaki-0.9.2.dist-info/METADATA
misaki-0.9.2.dist-info/WHEEL
misaki-0.9.2.dist-info/licenses/LICENSE
misaki-0.9.2.dist-info/RECORD
