Metadata-Version: 2.4
Name: misaki
Version: 0.9.2
Summary: G2P engine for TTS
Author-email: hexgrad <hello@hexgrad.com>
License:                                  Apache License
License-File: LICENSE
Classifier: License :: OSI Approved :: Apache Software License
Classifier: Operating System :: OS Independent
Classifier: Programming Language :: Python :: 3
Requires-Python: <3.13,>=3.8
Requires-Dist: addict
Requires-Dist: regex
Provides-Extra: en
Requires-Dist: espeakng-loader; extra == 'en'
Requires-Dist: num2words; extra == 'en'
Requires-Dist: phonemizer-fork; extra == 'en'
Requires-Dist: spacy; extra == 'en'
Requires-Dist: spacy-curated-transformers; extra == 'en'
Provides-Extra: ja
Requires-Dist: fugashi; extra == 'ja'
Requires-Dist: jaconv; extra == 'ja'
Requires-Dist: mojimoji; extra == 'ja'
Requires-Dist: pyopenjtalk-plus; extra == 'ja'
Requires-Dist: unidic-lite; extra == 'ja'
Provides-Extra: ko
Requires-Dist: jamo; extra == 'ko'
Requires-Dist: nltk; extra == 'ko'
Provides-Extra: vi
Requires-Dist: num2words; extra == 'vi'
Requires-Dist: spacy; extra == 'vi'
Requires-Dist: spacy-curated-transformers; extra == 'vi'
Requires-Dist: underthesea; extra == 'vi'
Provides-Extra: zh
Requires-Dist: cn2an; extra == 'zh'
Requires-Dist: jieba; extra == 'zh'
Requires-Dist: ordered-set; extra == 'zh'
Requires-Dist: pypinyin; extra == 'zh'
Requires-Dist: pypinyin-dict; extra == 'zh'
